LICENSE.md
MANIFEST.in
README.md
setup.py
admin_berry/__init__.py
admin_berry/admin.py
admin_berry/apps.py
admin_berry/forms.py
admin_berry/models.py
admin_berry/tests.py
admin_berry/urls.py
admin_berry/utils.py
admin_berry/views.py
admin_berry/migrations/__init__.py
admin_berry/static/assets/css/forms.css
admin_berry/static/assets/css/style-preset.css
admin_berry/static/assets/css/style.css
admin_berry/static/assets/css/widgets.css
admin_berry/static/assets/css/plugins/animate.min.css
admin_berry/static/assets/css/plugins/bootstrap.min.css
admin_berry/static/assets/fonts/material.css
admin_berry/static/assets/fonts/tabler-icons.min.css
admin_berry/static/assets/fonts/inter/Inter-Bold.woff
admin_berry/static/assets/fonts/inter/Inter-Bold.woff2
admin_berry/static/assets/fonts/inter/Inter-Medium.woff
admin_berry/static/assets/fonts/inter/Inter-Medium.woff2
admin_berry/static/assets/fonts/inter/Inter-Regular.woff
admin_berry/static/assets/fonts/inter/Inter-Regular.woff2
admin_berry/static/assets/fonts/inter/Inter-SemiBold.woff
admin_berry/static/assets/fonts/inter/Inter-SemiBold.woff2
admin_berry/static/assets/fonts/inter/inter.css
admin_berry/static/assets/fonts/material/material.woff2
admin_berry/static/assets/fonts/tabler/tabler-icons.eot
admin_berry/static/assets/fonts/tabler/tabler-icons.svg
admin_berry/static/assets/fonts/tabler/tabler-icons.ttf
admin_berry/static/assets/fonts/tabler/tabler-icons.woff
admin_berry/static/assets/fonts/tabler/tabler-icons.woff2
admin_berry/static/assets/images/favicon.svg
admin_berry/static/assets/images/logo-dark.svg
admin_berry/static/assets/images/logo-white.svg
admin_berry/static/assets/images/logo.svg
admin_berry/static/assets/images/authentication/google-icon.svg
admin_berry/static/assets/images/user/avatar-1.jpg
admin_berry/static/assets/images/user/avatar-10.jpg
admin_berry/static/assets/images/user/avatar-2.jpg
admin_berry/static/assets/images/user/avatar-3.jpg
admin_berry/static/assets/images/user/avatar-4.jpg
django_admin_berry.egg-info/PKG-INFO
django_admin_berry.egg-info/SOURCES.txt
django_admin_berry.egg-info/dependency_links.txt
django_admin_berry.egg-info/not-zip-safe
django_admin_berry.egg-info/top_level.txt
